setup.py
xserver/__init__.py
xserver.egg-info/PKG-INFO
xserver.egg-info/SOURCES.txt
xserver.egg-info/dependency_links.txt
xserver.egg-info/entry_points.txt
xserver.egg-info/requires.txt
xserver.egg-info/top_level.txt
xserver/_draft/__init__.py
xserver/_draft/install_packages.py
xserver/client/__init__.py
xserver/client/hello.py
xserver/client/init/__init__.py
xserver/client/init/deploy_env.py
xserver/client/init/ssh.py
xserver/client/install/__init__.py
xserver/client/install/container_ipfs.py
xserver/client/install/docker.py
xserver/client/install/git.py
xserver/client/install/xserver.py
xserver/client/maintain/__init__.py
xserver/client/maintain/project.py
xserver/client/maintain/server.py
xserver/client/utils/__init__.py
xserver/client/utils/fab.py
xserver/client/utils/remote_docker_utils.py
xserver/deploy_files/__init__.py
xserver/deploy_files/compile.py
xserver/deploy_files/farbox/__init__.py
xserver/deploy_files/farbox/files.py
xserver/deploy_files/farbox/configs/__init__.py
xserver/deploy_files/farbox/configs/backend_jobs.py
xserver/deploy_files/farbox/configs/gunicorn.conf.py
xserver/deploy_files/farbox/configs/gunicorn_websocket.conf.py
xserver/deploy_files/firstweb/__init__.py
xserver/deploy_files/firstweb/files.py
xserver/deploy_files/ipfs/__init__.py
xserver/deploy_files/ipfs/files.py
xserver/deploy_files/web_app_demo/__init__.py
xserver/deploy_files/web_app_demo/app.py
xserver/deploy_files/web_app_demo/files.py
xserver/docker_image/__init__.py
xserver/docker_image/console.py
xserver/docker_image/utils.py
xserver/docker_image/files/__init__.py
xserver/docker_image/files/_dump.py
xserver/docker_image/files/firstweb.py
xserver/docker_image/files/ipfs.py
xserver/docker_image/files/mongodb.py
xserver/docker_image/files/pyweb.py
xserver/docker_image/files/ssdb.py
xserver/docker_image/files/supervisor.py
xserver/docker_image/files/xserver_demo_app.py
xserver/docker_image/templates/__init__.py
xserver/docker_image/templates/build_images.py
xserver/docker_image/templates/utils.py
xserver/helper/__init__.py
xserver/helper/package_utils.py
xserver/helper/private_key.py
xserver/helper/console/__init__.py
xserver/helper/console/iptables.py
