Metadata-Version: 1.0
Name: xserver
Version: 0.0.7210
Summary: xserver for deploying
Home-page: UNKNOWN
Author: Hepochen
Author-email: hepochen@gmail.com
License: UNKNOWN
Platform: linux
